deeplens/__init__.py
deeplens/basics.py
deeplens/camera.py
deeplens/diffraclens.py
deeplens/geolens.py
deeplens/hybridlens.py
deeplens/lens.py
deeplens/paraxiallens.py
deeplens/psfnetlens.py
deeplens/utils.py
deeplens/geolens_pkg/__init__.py
deeplens/geolens_pkg/eval.py
deeplens/geolens_pkg/io.py
deeplens/geolens_pkg/optim.py
deeplens/geolens_pkg/tolerance.py
deeplens/geolens_pkg/utils.py
deeplens/geolens_pkg/view_3d.py
deeplens/geolens_pkg/vis.py
deeplens/network/__init__.py
deeplens/network/dataset.py
deeplens/network/loss/__init__.py
deeplens/network/loss/perceptual_loss.py
deeplens/network/loss/psnr_loss.py
deeplens/network/loss/ssim_loss.py
deeplens/network/reconstruction/__init__.py
deeplens/network/reconstruction/nafnet.py
deeplens/network/reconstruction/restormer.py
deeplens/network/reconstruction/swinir.py
deeplens/network/reconstruction/unet.py
deeplens/network/surrogate/__init__.py
deeplens/network/surrogate/mlp.py
deeplens/network/surrogate/mlpconv.py
deeplens/network/surrogate/modulate_siren.py
deeplens/network/surrogate/psfnet_mplconv.py
deeplens/network/surrogate/siren.py
deeplens/optics/__init__.py
deeplens/optics/loss.py
deeplens/optics/materials.py
deeplens/optics/monte_carlo.py
deeplens/optics/psf.py
deeplens/optics/ray.py
deeplens/optics/utils.py
deeplens/optics/wave.py
deeplens/optics/diffractive_surface/__init__.py
deeplens/optics/diffractive_surface/binary2.py
deeplens/optics/diffractive_surface/diffractive.py
deeplens/optics/diffractive_surface/fresnel.py
deeplens/optics/diffractive_surface/grating.py
deeplens/optics/diffractive_surface/pixel2d.py
deeplens/optics/diffractive_surface/thinlens.py
deeplens/optics/diffractive_surface/zernike.py
deeplens/optics/geometric_surface/__init__.py
deeplens/optics/geometric_surface/aperture.py
deeplens/optics/geometric_surface/aspheric.py
deeplens/optics/geometric_surface/aspheric_norm.py
deeplens/optics/geometric_surface/base.py
deeplens/optics/geometric_surface/cubic.py
deeplens_core-1.3.2.dist-info/licenses/LICENSE
deeplens_core-1.3.2.dist-info/METADATA
deeplens_core-1.3.2.dist-info/WHEEL
deeplens_core-1.3.2.dist-info/top_level.txt
deeplens_core-1.3.2.dist-info/RECORD
