Metadata-Version: 2.4
Name: deeplens-core
Version: 1.3.2
Summary: DeepLens: differentiable optical lens simulator for end-to-end cameras.
Author-email: Xinge Yang <xinge.yang@kaust.edu.sa>
License: Apache-2.0
Project-URL: Homepage, https://github.com/singer-yang/DeepLens
Project-URL: Repository, https://github.com/singer-yang/DeepLens
Project-URL: Documentation, https://deeplens.readthedocs.io/en/latest/
Classifier: License :: OSI Approved :: Apache Software License
Classifier: Programming Language :: Python :: 3
Classifier: Programming Language :: Python :: 3.12
Classifier: Programming Language :: Python :: 3.13
Requires-Python: >=3.12
License-File: LICENSE
Requires-Dist: torch
Requires-Dist: torchvision
Requires-Dist: opencv-python>=4.8.0
Requires-Dist: matplotlib>=3.7.0
Requires-Dist: scikit-image>=0.20.0
Requires-Dist: transformers>=4.30.0
Requires-Dist: lpips>=0.1.4
Requires-Dist: einops>=0.7.0
Requires-Dist: timm>=0.9.0
Requires-Dist: tqdm>=4.65.0
Requires-Dist: wandb>=0.15.0
Provides-Extra: dev
Requires-Dist: jupyter>=1.0.0; extra == "dev"
Requires-Dist: notebook>=7.0.0; extra == "dev"
Requires-Dist: ipywidgets>=8.0.0; extra == "dev"
Dynamic: license-file
